{
  "type": "construction_table",
  "knowledge": true,
  "criteria": [
    {
      "name": "rockbottom/pickup_item",
      "params": {
        "item": "iron_processed"
      }
    }
  ],
  "tools": [
    {
      "name": "rockbottom/hammer",
      "usage": 9
    },
    {
      "name": "rockbottom/chisel",
      "usage": 4
    },
    {
      "name": "rockbottom/wrench",
      "usage": 2
    }
  ],
  "outputs": [
    {
      "name": "rocksolid/separator"
    }
  ],
  "inputs": [
    {
      "name": "stone",
      "amount": 50
    },
    {
      "name": "bronze_processed",
      "amount": 10
    },
    {
      "name": "iron_processed",
      "amount": 8
    },
    {
      "name": "coal",
      "amount": 12
    }
  ],
  "skill": 0.40
}